qmk-1.1.7.dist-info/licenses/LICENSE
qmk_cli/__init__.py
qmk_cli/git.py
qmk_cli/helpers.py
qmk_cli/script_qmk.py
qmk_cli/subcommands/__init__.py
qmk_cli/subcommands/clone.py
qmk_cli/subcommands/console.py
qmk_cli/subcommands/env.py
qmk_cli/subcommands/setup.py
qmk-1.1.7.dist-info/METADATA
qmk-1.1.7.dist-info/WHEEL
qmk-1.1.7.dist-info/entry_points.txt
qmk-1.1.7.dist-info/top_level.txt
qmk-1.1.7.dist-info/RECORD
