Metadata-Version: 2.4
Name: qmk
Version: 1.1.7
Summary: A program to help users work with QMK Firmware.
Author: skullydazed
Author-email: skullydazed@gmail.com
License: MIT License
Project-URL: Bug Tracker, https://github.com/qmk/qmk_cli/issues
Project-URL: Documentation, https://docs.qmk.fm/#/cli
Project-URL: Homepage, https://qmk.fm/
Project-URL: Source, https://github.com/qmk/qmk_cli/
Classifier: Development Status :: 3 - Alpha
Classifier: Environment :: Console
Classifier: Intended Audience :: Developers
Classifier: Intended Audience :: System Administrators
Classifier: Intended Audience :: End Users/Desktop
Classifier: License :: OSI Approved :: MIT License
Classifier: Natural Language :: English
Classifier: Programming Language :: Python :: 3 :: Only
Classifier: Topic :: Scientific/Engineering
Classifier: Topic :: Software Development
Classifier: Topic :: Utilities
Requires-Python: >=3.9
License-File: LICENSE
Requires-Dist: hid
Requires-Dist: milc>=1.9.0
Requires-Dist: pyusb
Requires-Dist: dotty-dict
Requires-Dist: hjson
Requires-Dist: jsonschema>=4
Requires-Dist: pillow
Requires-Dist: pygments
Requires-Dist: pyserial
Dynamic: license-file
